rolobeltrao/__init__.py
rolobeltrao/rolobeltrao_modulo.py
pacote_rolobeltrao-0.1.2.dist-info/METADATA
pacote_rolobeltrao-0.1.2.dist-info/WHEEL
pacote_rolobeltrao-0.1.2.dist-info/top_level.txt
pacote_rolobeltrao-0.1.2.dist-info/RECORD
