Metadata-Version: 2.4
Name: pacote-rolobeltrao
Version: 0.1.2
Summary: Estudando módulos com o PyPI
Home-page: https://github.com/seu-usuario/meu_pacote
Author: Rolo Beltrão
Author-email: rolobeltrao.2025@gmail.com
Classifier: Programming Language :: Python :: 3
Classifier: License :: OSI Approved :: MIT License
Classifier: Operating System :: OS Independent
Requires-Python: >=3.6
Dynamic: author
Dynamic: author-email
Dynamic: classifier
Dynamic: description-content-type
Dynamic: home-page
Dynamic: requires-python
Dynamic: summary
